<?xml version="1.0" encoding="UTF-8"?>
<orv:ObsReview xmlns:ent="Alma/CommonEntity" xmlns:val="Alma/ValueTypes"
    xmlns:prp="Alma/ObsPrep/ObsProposal"
    xmlns:orv="Alma/ObsPrep/ObsReview"
    xmlns:ps="Alma/ObsPrep/ProjectStatus"
    xmlns:oat="Alma/ObsPrep/ObsAttachment"
    xmlns:prj="Alma/ObsPrep/ObsProject"
    xmlns:sbl="Alma/ObsPrep/SchedBlock"
    xmlns:xsi="http://www.w3.org/2001/XMLSchema-instance"
    schemaVersion="13" revision="13" almatype="APDM::ObsReview" xsi:type="orv:ObsReview">
    <prj:ObsPlan status="Phase1Submitted" entityPartId="X17372053" almatype="APDM::ObsUnitSet">
        <prj:name>ObsUnitSet</prj:name>
        <prj:note></prj:note>
        <prj:ObsUnitControl arrayRequested="TWELVE-M">
            <prj:maximumTime unit="min">480.0</prj:maximumTime>
            <prj:userPriority>0</prj:userPriority>
            <prj:estimatedExecutionTime unit="min">480.0</prj:estimatedExecutionTime>
            <prj:tacPriority>0</prj:tacPriority>
            <prj:aggregatedExecutionCount>4</prj:aggregatedExecutionCount>
            <prj:CalibrationRequirements>
                <prj:pointingAccuracy unit="arcsec">0.0</prj:pointingAccuracy>
            </prj:CalibrationRequirements>
        </prj:ObsUnitControl>
        <prj:ObsProjectRef entityId="uid://A001/X1ee/X26b"
            entityTypeName="ObsProject" documentVersion="1"/>
        <prj:scienceProcessingScript></prj:scienceProcessingScript>
        <prj:runSciencePipeline>false</prj:runSciencePipeline>
        <prj:ObsUnitSet status="NewPhase1" entityPartId="X14994417" almatype="APDM::ObsUnitSet">
            <prj:name>SG OUS (HF(1-0) in IRAS Z21293-0154)</prj:name>
            <prj:note></prj:note>
            <prj:ObsUnitControl arrayRequested="TWELVE-M">
                <prj:maximumTime unit="min">240.0</prj:maximumTime>
                <prj:userPriority>0</prj:userPriority>
                <prj:estimatedExecutionTime unit="min">240.0</prj:estimatedExecutionTime>
                <prj:tacPriority>0</prj:tacPriority>
                <prj:aggregatedExecutionCount>2</prj:aggregatedExecutionCount>
                <prj:CalibrationRequirements>
                    <prj:pointingAccuracy unit="arcsec">0.0</prj:pointingAccuracy>
                </prj:CalibrationRequirements>
            </prj:ObsUnitControl>
            <prj:ObsProjectRef entityId="uid://A001/X1ee/X26b"
                entityTypeName="ObsProject" documentVersion="1"/>
            <prj:scienceProcessingScript></prj:scienceProcessingScript>
            <prj:runSciencePipeline>false</prj:runSciencePipeline>
            <prj:ObsUnitSet status="NewPhase2" entityPartId="X17392295" almatype="APDM::ObsUnitSet">
                <prj:name>Group OUS</prj:name>
                <prj:note></prj:note>
                <prj:ObsUnitControl arrayRequested="TWELVE-M">
                    <prj:maximumTime unit="min">240.0</prj:maximumTime>
                    <prj:userPriority>0</prj:userPriority>
                    <prj:estimatedExecutionTime unit="min">240.0</prj:estimatedExecutionTime>
                    <prj:tacPriority>0</prj:tacPriority>
                    <prj:aggregatedExecutionCount>2</prj:aggregatedExecutionCount>
                    <prj:CalibrationRequirements>
                        <prj:pointingAccuracy unit="arcsec">0.0</prj:pointingAccuracy>
                    </prj:CalibrationRequirements>
                </prj:ObsUnitControl>
                <prj:ObsProjectRef entityId="uid://A001/X1ee/X26b"
                    entityTypeName="ObsProject" documentVersion="1"/>
                <prj:scienceProcessingScript></prj:scienceProcessingScript>
                <prj:runSciencePipeline>false</prj:runSciencePipeline>
                <prj:ObsUnitSet status="NewPhase2"
                    entityPartId="X24098812" almatype="APDM::ObsUnitSet">
                    <prj:name>Member OUS (Z21293-0154)</prj:name>
                    <prj:note></prj:note>
                    <prj:ObsUnitControl arrayRequested="TWELVE-M">
                        <prj:maximumTime unit="min">240.0</prj:maximumTime>
                        <prj:userPriority>0</prj:userPriority>
                        <prj:estimatedExecutionTime unit="min">240.0</prj:estimatedExecutionTime>
                        <prj:tacPriority>0</prj:tacPriority>
                        <prj:aggregatedExecutionCount>2</prj:aggregatedExecutionCount>
                        <prj:CalibrationRequirements>
                            <prj:pointingAccuracy unit="arcsec">0.0</prj:pointingAccuracy>
                        </prj:CalibrationRequirements>
                    </prj:ObsUnitControl>
                    <prj:ObsProjectRef entityId="uid://A001/X1ee/X26b"
                        entityTypeName="ObsProject" documentVersion="1"/>
                    <prj:scienceProcessingScript></prj:scienceProcessingScript>
                    <prj:runSciencePipeline>true</prj:runSciencePipeline>
                    <prj:DataProcessingParameters projectType="Continuum">
                        <prj:angularResolution unit="arcsec">0.7</prj:angularResolution>
                    </prj:DataProcessingParameters>
                    <prj:SchedBlockRef entityId="uid://A001/X200/X952"
                        entityTypeName="SchedBlock" documentVersion="1"/>
                </prj:ObsUnitSet>
            </prj:ObsUnitSet>
        </prj:ObsUnitSet>
        <prj:ObsUnitSet status="NewPhase1" entityPartId="X8529980" almatype="APDM::ObsUnitSet">
            <prj:name>SG OUS (CH(1-1) in IRAS Z21293-0154)</prj:name>
            <prj:note></prj:note>
            <prj:ObsUnitControl arrayRequested="TWELVE-M">
                <prj:maximumTime unit="min">120.0</prj:maximumTime>
                <prj:userPriority>0</prj:userPriority>
                <prj:estimatedExecutionTime unit="min">120.0</prj:estimatedExecutionTime>
                <prj:tacPriority>0</prj:tacPriority>
                <prj:aggregatedExecutionCount>1</prj:aggregatedExecutionCount>
                <prj:CalibrationRequirements>
                    <prj:pointingAccuracy unit="arcsec">0.0</prj:pointingAccuracy>
                </prj:CalibrationRequirements>
            </prj:ObsUnitControl>
            <prj:ObsProjectRef entityId="uid://A001/X1ee/X26b"
                entityTypeName="ObsProject" documentVersion="1"/>
            <prj:scienceProcessingScript></prj:scienceProcessingScript>
            <prj:runSciencePipeline>false</prj:runSciencePipeline>
            <prj:ObsUnitSet status="NewPhase2" entityPartId="X18856179" almatype="APDM::ObsUnitSet">
                <prj:name>Group OUS</prj:name>
                <prj:note></prj:note>
                <prj:ObsUnitControl arrayRequested="TWELVE-M">
                    <prj:maximumTime unit="min">120.0</prj:maximumTime>
                    <prj:userPriority>0</prj:userPriority>
                    <prj:estimatedExecutionTime unit="min">120.0</prj:estimatedExecutionTime>
                    <prj:tacPriority>0</prj:tacPriority>
                    <prj:aggregatedExecutionCount>1</prj:aggregatedExecutionCount>
                    <prj:CalibrationRequirements>
                        <prj:pointingAccuracy unit="arcsec">0.0</prj:pointingAccuracy>
                    </prj:CalibrationRequirements>
                </prj:ObsUnitControl>
                <prj:ObsProjectRef entityId="uid://A001/X1ee/X26b"
                    entityTypeName="ObsProject" documentVersion="1"/>
                <prj:scienceProcessingScript></prj:scienceProcessingScript>
                <prj:runSciencePipeline>false</prj:runSciencePipeline>
                <prj:ObsUnitSet status="NewPhase2"
                    entityPartId="X14271683" almatype="APDM::ObsUnitSet">
                    <prj:name>Member OUS (Z21293-0154)</prj:name>
                    <prj:note></prj:note>
                    <prj:ObsUnitControl arrayRequested="TWELVE-M">
                        <prj:maximumTime unit="min">120.0</prj:maximumTime>
                        <prj:userPriority>0</prj:userPriority>
                        <prj:estimatedExecutionTime unit="min">120.0</prj:estimatedExecutionTime>
                        <prj:tacPriority>0</prj:tacPriority>
                        <prj:aggregatedExecutionCount>1</prj:aggregatedExecutionCount>
                        <prj:CalibrationRequirements>
                            <prj:pointingAccuracy unit="arcsec">0.0</prj:pointingAccuracy>
                        </prj:CalibrationRequirements>
                    </prj:ObsUnitControl>
                    <prj:ObsProjectRef entityId="uid://A001/X1ee/X26b"
                        entityTypeName="ObsProject" documentVersion="1"/>
                    <prj:scienceProcessingScript></prj:scienceProcessingScript>
                    <prj:runSciencePipeline>true</prj:runSciencePipeline>
                    <prj:DataProcessingParameters projectType="Continuum">
                        <prj:angularResolution unit="arcsec">0.7</prj:angularResolution>
                    </prj:DataProcessingParameters>
                    <prj:SchedBlockRef entityId="uid://A001/X200/X953"
                        entityTypeName="SchedBlock" documentVersion="1"/>
                </prj:ObsUnitSet>
            </prj:ObsUnitSet>
        </prj:ObsUnitSet>
        <prj:ObsUnitSet status="NewPhase1" entityPartId="X16719832" almatype="APDM::ObsUnitSet">
            <prj:name>SG OUS (CO(7-6) in IRAS Z12193-0154)</prj:name>
            <prj:note></prj:note>
            <prj:ObsUnitControl arrayRequested="TWELVE-M">
                <prj:maximumTime unit="min">120.0</prj:maximumTime>
                <prj:userPriority>0</prj:userPriority>
                <prj:estimatedExecutionTime unit="min">120.0</prj:estimatedExecutionTime>
                <prj:tacPriority>0</prj:tacPriority>
                <prj:aggregatedExecutionCount>1</prj:aggregatedExecutionCount>
                <prj:CalibrationRequirements>
                    <prj:pointingAccuracy unit="arcsec">0.0</prj:pointingAccuracy>
                </prj:CalibrationRequirements>
            </prj:ObsUnitControl>
            <prj:ObsProjectRef entityId="uid://A001/X1ee/X26b"
                entityTypeName="ObsProject" documentVersion="1"/>
            <prj:scienceProcessingScript></prj:scienceProcessingScript>
            <prj:runSciencePipeline>false</prj:runSciencePipeline>
            <prj:ObsUnitSet status="NewPhase2" entityPartId="X25406400" almatype="APDM::ObsUnitSet">
                <prj:name>Group OUS</prj:name>
                <prj:note></prj:note>
                <prj:ObsUnitControl arrayRequested="TWELVE-M">
                    <prj:maximumTime unit="min">120.0</prj:maximumTime>
                    <prj:userPriority>0</prj:userPriority>
                    <prj:estimatedExecutionTime unit="min">120.0</prj:estimatedExecutionTime>
                    <prj:tacPriority>0</prj:tacPriority>
                    <prj:aggregatedExecutionCount>1</prj:aggregatedExecutionCount>
                    <prj:CalibrationRequirements>
                        <prj:pointingAccuracy unit="arcsec">0.0</prj:pointingAccuracy>
                    </prj:CalibrationRequirements>
                </prj:ObsUnitControl>
                <prj:ObsProjectRef entityId="uid://A001/X1ee/X26b"
                    entityTypeName="ObsProject" documentVersion="1"/>
                <prj:scienceProcessingScript></prj:scienceProcessingScript>
                <prj:runSciencePipeline>false</prj:runSciencePipeline>
                <prj:ObsUnitSet status="NewPhase2"
                    entityPartId="X30436804" almatype="APDM::ObsUnitSet">
                    <prj:name>Member OUS (Z21293-0154)</prj:name>
                    <prj:note></prj:note>
                    <prj:ObsUnitControl arrayRequested="TWELVE-M">
                        <prj:maximumTime unit="min">120.0</prj:maximumTime>
                        <prj:userPriority>0</prj:userPriority>
                        <prj:estimatedExecutionTime unit="min">120.0</prj:estimatedExecutionTime>
                        <prj:tacPriority>0</prj:tacPriority>
                        <prj:aggregatedExecutionCount>1</prj:aggregatedExecutionCount>
                        <prj:CalibrationRequirements>
                            <prj:pointingAccuracy unit="arcsec">0.0</prj:pointingAccuracy>
                        </prj:CalibrationRequirements>
                    </prj:ObsUnitControl>
                    <prj:ObsProjectRef entityId="uid://A001/X1ee/X26b"
                        entityTypeName="ObsProject" documentVersion="1"/>
                    <prj:scienceProcessingScript></prj:scienceProcessingScript>
                    <prj:runSciencePipeline>true</prj:runSciencePipeline>
                    <prj:DataProcessingParameters projectType="Continuum">
                        <prj:angularResolution unit="arcsec">0.7</prj:angularResolution>
                    </prj:DataProcessingParameters>
                    <prj:SchedBlockRef entityId="uid://A001/X200/X954"
                        entityTypeName="SchedBlock" documentVersion="1"/>
                </prj:ObsUnitSet>
            </prj:ObsUnitSet>
        </prj:ObsUnitSet>
    </prj:ObsPlan>
    <orv:ObsReviewEntity entityId="uid://A001/X200/X951"
        entityIdEncrypted="-- id encryption not implemented --"
        entityTypeName="ObsReview" schemaVersion="13" documentVersion="1"/>
    <orv:ObsProjectRef entityId="uid://A001/X1ee/X26b"
        entityTypeName="ObsProject" documentVersion="1"/>
</orv:ObsReview>
