<?xml version="1.0" encoding="UTF-8"?>
<prp:ObsProposal xmlns:ent="Alma/CommonEntity"
    xmlns:val="Alma/ValueTypes" xmlns:prp="Alma/ObsPrep/ObsProposal"
    xmlns:orv="Alma/ObsPrep/ObsReview"
    xmlns:ps="Alma/ObsPrep/ProjectStatus"
    xmlns:oat="Alma/ObsPrep/ObsAttachment"
    xmlns:prj="Alma/ObsPrep/ObsProject"
    xmlns:sbl="Alma/ObsPrep/SchedBlock"
    xmlns:xsi="http://www.w3.org/2001/XMLSchema-instance"
    schemaVersion="13" revision="13" almatype="APDM::ObsProposal" xsi:type="prp:ObsProposal">
    <prj:ScienceGoal mode="Other">
        <prj:name>Band 3 Long Baseline</prj:name>
        <prj:note></prj:note>
        <prj:estimatedTotalTime unit="min">364.714</prj:estimatedTotalTime>
        <prj:userPriority>0</prj:userPriority>
        <prj:requiredReceiverBands>ALMA_RB_03</prj:requiredReceiverBands>
        <prj:estimated12mTime unit="min">364.714</prj:estimated12mTime>
        <prj:estimated7mTime unit="s">0.0</prj:estimated7mTime>
        <prj:estimatedTPTime unit="s">0.0</prj:estimatedTPTime>
        <prj:estimatedACATime unit="s">0.0</prj:estimatedACATime>
        <prj:CalibrationSetupParameters selection="system"/>
        <prj:PerformanceParameters desiredSensitivityFrequencyMeasure="User">
            <prj:desiredAngularResolution unit="arcsec" userUnit="arcsec">0.077</prj:desiredAngularResolution>
            <prj:desiredLargestScale unit="arcsec">1.0</prj:desiredLargestScale>
            <prj:desiredSensitivity unit="Jy" userUnit="uJy">3.999999999999998E-4</prj:desiredSensitivity>
            <prj:desiredDynamicRange>1.0</prj:desiredDynamicRange>
            <prj:representativeFrequency unit="GHz">99.23483806154033</prj:representativeFrequency>
            <prj:useACA>false</prj:useACA>
            <prj:isTimeConstrained>false</prj:isTimeConstrained>
            <prj:useTP>false</prj:useTP>
            <prj:desiredSDSensitivity unit="Jy" userUnit="Jy">0.0</prj:desiredSDSensitivity>
            <prj:isPointSource>false</prj:isPointSource>
            <prj:desiredSensitivityReferenceFrequencyWidth unit="GHz" userUnit="km/s">0.003310117897013284</prj:desiredSensitivityReferenceFrequencyWidth>
            <prj:needsMoreTime>false</prj:needsMoreTime>
            <prj:desiredACASensitivity unit="mJy" userUnit="Jy">2.529526005019975</prj:desiredACASensitivity>
            <prj:desiredTPSensitivity unit="mJy" userUnit="Jy">5.796550698475772</prj:desiredTPSensitivity>
            <prj:isScheduleConstrained>false</prj:isScheduleConstrained>
            <prj:desiredTime unit="min">0.0</prj:desiredTime>
        </prj:PerformanceParameters>
        <prj:SpectralSetupParameters polarisation="DOUBLE" type="full">
            <prj:representativeFrequency unit="GHz">99.311</prj:representativeFrequency>
            <prj:userRepresentativeFrequency>false</prj:userRepresentativeFrequency>
            <prj:singleContinuumFrequency unit="GHz">0.0</prj:singleContinuumFrequency>
            <prj:ScienceSpectralWindow groupResourceUse="FULL">
                <prj:index>0</prj:index>
                <prj:AdvancedWindowSetup smoothingFunction="HANNING">
                    <prj:smoothingFactor>4</prj:smoothingFactor>
                    <prj:oversampling>false</prj:oversampling>
                    <prj:addedSensitivity>false</prj:addedSensitivity>
                    <prj:useImage>false</prj:useImage>
                    <prj:useThis>true</prj:useThis>
                </prj:AdvancedWindowSetup>
                <prj:transitionName>13CO</prj:transitionName>
                <prj:centerFrequency unit="GHz">110.354</prj:centerFrequency>
                <prj:bandWidth unit="MHz" userUnit="GHz">2000.0</prj:bandWidth>
                <prj:spectralResolution unit="kHz" userUnit="GHz">488.28125000000006</prj:spectralResolution>
                <prj:groupIndex>3</prj:groupIndex>
                <prj:isSkyFrequency>false</prj:isSkyFrequency>
                <prj:representativeWindow>false</prj:representativeWindow>
            </prj:ScienceSpectralWindow>
            <prj:ScienceSpectralWindow groupResourceUse="FULL">
                <prj:index>0</prj:index>
                <prj:AdvancedWindowSetup smoothingFunction="HANNING">
                    <prj:smoothingFactor>4</prj:smoothingFactor>
                    <prj:oversampling>false</prj:oversampling>
                    <prj:addedSensitivity>false</prj:addedSensitivity>
                    <prj:useImage>false</prj:useImage>
                    <prj:useThis>true</prj:useThis>
                </prj:AdvancedWindowSetup>
                <prj:transitionName>C18O</prj:transitionName>
                <prj:centerFrequency unit="GHz">109.354</prj:centerFrequency>
                <prj:bandWidth unit="MHz" userUnit="GHz">2000.0</prj:bandWidth>
                <prj:spectralResolution unit="MHz" userUnit="GHz">0.48828125</prj:spectralResolution>
                <prj:groupIndex>2</prj:groupIndex>
                <prj:isSkyFrequency>false</prj:isSkyFrequency>
                <prj:representativeWindow>false</prj:representativeWindow>
            </prj:ScienceSpectralWindow>
            <prj:ScienceSpectralWindow groupResourceUse="FULL">
                <prj:index>0</prj:index>
                <prj:AdvancedWindowSetup smoothingFunction="HANNING">
                    <prj:smoothingFactor>1</prj:smoothingFactor>
                    <prj:oversampling>false</prj:oversampling>
                    <prj:addedSensitivity>false</prj:addedSensitivity>
                    <prj:useImage>false</prj:useImage>
                    <prj:useThis>true</prj:useThis>
                </prj:AdvancedWindowSetup>
                <prj:transitionName>H(40)a</prj:transitionName>
                <prj:centerFrequency unit="GHz">99.311</prj:centerFrequency>
                <prj:bandWidth unit="MHz" userUnit="GHz">2000.0</prj:bandWidth>
                <prj:spectralResolution unit="kHz" userUnit="GHz">488.28125000000006</prj:spectralResolution>
                <prj:groupIndex>1</prj:groupIndex>
                <prj:isSkyFrequency>false</prj:isSkyFrequency>
                <prj:representativeWindow>true</prj:representativeWindow>
            </prj:ScienceSpectralWindow>
            <prj:ScienceSpectralWindow groupResourceUse="FULL">
                <prj:index>0</prj:index>
                <prj:AdvancedWindowSetup smoothingFunction="HANNING">
                    <prj:smoothingFactor>4</prj:smoothingFactor>
                    <prj:oversampling>false</prj:oversampling>
                    <prj:addedSensitivity>false</prj:addedSensitivity>
                    <prj:useImage>false</prj:useImage>
                    <prj:useThis>true</prj:useThis>
                </prj:AdvancedWindowSetup>
                <prj:transitionName>CS</prj:transitionName>
                <prj:centerFrequency unit="GHz">97.311</prj:centerFrequency>
                <prj:bandWidth unit="MHz" userUnit="GHz">2000.0</prj:bandWidth>
                <prj:spectralResolution unit="MHz" userUnit="GHz">0.48828125</prj:spectralResolution>
                <prj:groupIndex>0</prj:groupIndex>
                <prj:isSkyFrequency>false</prj:isSkyFrequency>
                <prj:splatalogId>3952764</prj:splatalogId>
                <prj:representativeWindow>false</prj:representativeWindow>
            </prj:ScienceSpectralWindow>
        </prj:SpectralSetupParameters>
        <prj:TargetParameters solarSystemObject="Unspecified" type="F_MultiplePoints">
            <prj:sourceName>NGC_253</prj:sourceName>
            <prj:sourceCoordinates system="J2000" type="ABSOLUTE">
                <val:longitude unit="deg">11.8879</val:longitude>
                <val:latitude unit="deg">-25.28836111111111</val:latitude>
                <val:fieldName>None</val:fieldName>
            </prj:sourceCoordinates>
            <prj:pmRA unit="mas/yr">0.0</prj:pmRA>
            <prj:pmDec unit="mas/yr">0.0</prj:pmDec>
            <prj:parallax unit="mas">0.0</prj:parallax>
            <prj:nonSiderealMotion>false</prj:nonSiderealMotion>
            <prj:sourceEphemeris></prj:sourceEphemeris>
            <prj:sourceVelocity referenceSystem="lsrk" dopplerCalcType="RELATIVISTIC">
                <val:centerVelocity unit="km/s">230.0</val:centerVelocity>
            </prj:sourceVelocity>
            <prj:index>-1</prj:index>
            <prj:ExpectedProperties>
                <prj:expectedPeakFluxDensity unit="mJy">20.0</prj:expectedPeakFluxDensity>
                <prj:desiredPolarizationPercentage>0.0</prj:desiredPolarizationPercentage>
                <prj:expectedLineWidth unit="GHz" userUnit="km/s">0.009930353691039846</prj:expectedLineWidth>
                <prj:referenceFrequency unit="GHz">99.23483806154033</prj:referenceFrequency>
                <prj:expectedPeakLineFluxDensity unit="mJy">2.0</prj:expectedPeakLineFluxDensity>
                <prj:expectedSpectralDynamicRange>0.0</prj:expectedSpectralDynamicRange>
                <prj:expectedImageDynamicRange>0.0</prj:expectedImageDynamicRange>
                <prj:desiredLinePolarizationPercentage>0.0</prj:desiredLinePolarizationPercentage>
            </prj:ExpectedProperties>
            <prj:isMosaic>false</prj:isMosaic>
            <prj:SinglePoint>
                <prj:name></prj:name>
                <prj:centre system="J2000" type="RELATIVE">
                    <val:longitude unit="arcsec">0.0</val:longitude>
                    <val:latitude unit="arcsec">0.0</val:latitude>
                    <val:fieldName>NGC_253-1</val:fieldName>
                </prj:centre>
            </prj:SinglePoint>
        </prj:TargetParameters>
        <prj:TechnicalJustification>
            <prj:justificationText>To achieve maximum continuum sensitivity, we place four 2 GHz width spectral windows in the correlator setup. The target (NGC 253) is very active starburst galaxy and many molecular and atomic lines have been already detected (e.g. 2 mm line survey by Martin et al. 2006, ApJS 164, 450). To get accurate continuum image, it is indispensable to identify and isolate contamination of those line emission. For this purpose, a spectral (velocity) resolution obtained with the 2 GHz and 128 channel mode is too low (effective resolution is about 90 km/s) and it will cause failing to remove weak and/or narrow velocity width emission lines. Therefore, we request the 2 GHz bandwidth with 3840 channels mode.</prj:justificationText>
            <prj:justificationKey>ED_CORRELATOR</prj:justificationKey>
        </prj:TechnicalJustification>
        <prj:TechnicalJustification>
            <prj:justificationText>Apparent angular sizes of targets in our study are both compact (0.06~0.5 arcseconds) and extended (up to a few arcseconds) in both continuum and line. In the science goal, we aim to catch the compact sources. To maximize the science output from this project, we have to measure the target size or set strong upper limit to the size even if it is not resolved. Hence, we request highest achievable spatial resolution in the representative frequency (99 GHz), namely 0.08 arcseconds. 
Extended continuum and line emission up to 3 arcseconds are detected in our Cycle 0 data. But, the maximum angular scale in the relevant configuration (C36-8) is about just 1.1 arcseconds, consequently it's not possible to recover all the extended emission solely with the configuration. Hence, we set 1.1 arcseconds as the largest angular scale for this science goal, and set up another science goal to recover extended emission more than 1.1 arcseconds.</prj:justificationText>
            <prj:justificationKey>ED_ANGULAR_RESOLUTION</prj:justificationKey>
        </prj:TechnicalJustification>
        <prj:TechnicalJustification>
            <prj:justificationText>The primary aim of the science goal is to detect H40alpha emission line as well as continuum from a target source in 105 GHz with 0.08 arcsec (~1 parsec) scale. We expect the source has a peak flux density of 2 mJy/beam and a velocity width of 30 km/s. To achieve secure detection and, at the same time, to resolve the emission in velocity space, we require a 10 km/s velocity resolution. A fair signal-to-noise ratio of more than 5 is required for secure detection, and this sets a maximum map noise level of 0.4 mJy in 10 km/s resolution. About 2 hours on-source integration is required to reach the noise level, and a continuum sensitivity reaches about 10 uJy simultaneously. The target has typical continuum flux density of 2 mJy per beam, and the expected continuum sensitivity is quite sufficient.</prj:justificationText>
            <prj:justificationKey>ED_SENSITIVITY</prj:justificationKey>
        </prj:TechnicalJustification>
    </prj:ScienceGoal>
    <prj:ScienceGoal mode="Standard">
        <prj:name>Copy of Band 3 Long Baseline</prj:name>
        <prj:note></prj:note>
        <prj:estimatedTotalTime unit="min">139.71066667</prj:estimatedTotalTime>
        <prj:userPriority>0</prj:userPriority>
        <prj:requiredReceiverBands>ALMA_RB_03</prj:requiredReceiverBands>
        <prj:estimated12mTime unit="min">139.71066667</prj:estimated12mTime>
        <prj:estimated7mTime unit="s">0.0</prj:estimated7mTime>
        <prj:estimatedTPTime unit="s">0.0</prj:estimatedTPTime>
        <prj:estimatedACATime unit="s">0.0</prj:estimatedACATime>
        <prj:CalibrationSetupParameters selection="system"/>
        <prj:PerformanceParameters desiredSensitivityFrequencyMeasure="User">
            <prj:desiredAngularResolution unit="arcsec" userUnit="arcsec">0.5</prj:desiredAngularResolution>
            <prj:desiredLargestScale unit="arcsec">3.0</prj:desiredLargestScale>
            <prj:desiredSensitivity unit="Jy" userUnit="uJy">5.0E-4</prj:desiredSensitivity>
            <prj:desiredDynamicRange>1.0</prj:desiredDynamicRange>
            <prj:representativeFrequency unit="GHz">99.23483806154033</prj:representativeFrequency>
            <prj:useACA>false</prj:useACA>
            <prj:isTimeConstrained>false</prj:isTimeConstrained>
            <prj:useTP>false</prj:useTP>
            <prj:desiredSDSensitivity unit="Jy" userUnit="Jy">0.0</prj:desiredSDSensitivity>
            <prj:isPointSource>false</prj:isPointSource>
            <prj:desiredSensitivityReferenceFrequencyWidth unit="GHz" userUnit="km/s">0.003310117897013284</prj:desiredSensitivityReferenceFrequencyWidth>
            <prj:needsMoreTime>false</prj:needsMoreTime>
            <prj:desiredACASensitivity unit="mJy" userUnit="Jy">3.1619075062749697</prj:desiredACASensitivity>
            <prj:desiredTPSensitivity unit="mJy" userUnit="Jy">7.245688373094719</prj:desiredTPSensitivity>
            <prj:isScheduleConstrained>false</prj:isScheduleConstrained>
            <prj:desiredTime unit="min">0.0</prj:desiredTime>
        </prj:PerformanceParameters>
        <prj:SpectralSetupParameters polarisation="DOUBLE" type="full">
            <prj:representativeFrequency unit="GHz">99.311</prj:representativeFrequency>
            <prj:userRepresentativeFrequency>false</prj:userRepresentativeFrequency>
            <prj:singleContinuumFrequency unit="GHz">0.0</prj:singleContinuumFrequency>
            <prj:ScienceSpectralWindow groupResourceUse="FULL">
                <prj:index>0</prj:index>
                <prj:AdvancedWindowSetup smoothingFunction="HANNING">
                    <prj:smoothingFactor>4</prj:smoothingFactor>
                    <prj:oversampling>false</prj:oversampling>
                    <prj:addedSensitivity>false</prj:addedSensitivity>
                    <prj:useImage>false</prj:useImage>
                    <prj:useThis>true</prj:useThis>
                </prj:AdvancedWindowSetup>
                <prj:transitionName>13CO</prj:transitionName>
                <prj:centerFrequency unit="GHz">110.354</prj:centerFrequency>
                <prj:bandWidth unit="MHz" userUnit="GHz">2000.0</prj:bandWidth>
                <prj:spectralResolution unit="kHz" userUnit="GHz">488.28125000000006</prj:spectralResolution>
                <prj:groupIndex>3</prj:groupIndex>
                <prj:isSkyFrequency>false</prj:isSkyFrequency>
                <prj:representativeWindow>false</prj:representativeWindow>
            </prj:ScienceSpectralWindow>
            <prj:ScienceSpectralWindow groupResourceUse="FULL">
                <prj:index>0</prj:index>
                <prj:AdvancedWindowSetup smoothingFunction="HANNING">
                    <prj:smoothingFactor>4</prj:smoothingFactor>
                    <prj:oversampling>false</prj:oversampling>
                    <prj:addedSensitivity>false</prj:addedSensitivity>
                    <prj:useImage>false</prj:useImage>
                    <prj:useThis>true</prj:useThis>
                </prj:AdvancedWindowSetup>
                <prj:transitionName>C18O</prj:transitionName>
                <prj:centerFrequency unit="GHz">109.354</prj:centerFrequency>
                <prj:bandWidth unit="MHz" userUnit="GHz">2000.0</prj:bandWidth>
                <prj:spectralResolution unit="MHz" userUnit="GHz">0.48828125</prj:spectralResolution>
                <prj:groupIndex>2</prj:groupIndex>
                <prj:isSkyFrequency>false</prj:isSkyFrequency>
                <prj:representativeWindow>false</prj:representativeWindow>
            </prj:ScienceSpectralWindow>
            <prj:ScienceSpectralWindow groupResourceUse="FULL">
                <prj:index>0</prj:index>
                <prj:AdvancedWindowSetup smoothingFunction="HANNING">
                    <prj:smoothingFactor>1</prj:smoothingFactor>
                    <prj:oversampling>false</prj:oversampling>
                    <prj:addedSensitivity>false</prj:addedSensitivity>
                    <prj:useImage>false</prj:useImage>
                    <prj:useThis>true</prj:useThis>
                </prj:AdvancedWindowSetup>
                <prj:transitionName>H(40)a</prj:transitionName>
                <prj:centerFrequency unit="GHz">99.311</prj:centerFrequency>
                <prj:bandWidth unit="MHz" userUnit="GHz">2000.0</prj:bandWidth>
                <prj:spectralResolution unit="kHz" userUnit="GHz">488.28125000000006</prj:spectralResolution>
                <prj:groupIndex>1</prj:groupIndex>
                <prj:isSkyFrequency>false</prj:isSkyFrequency>
                <prj:representativeWindow>true</prj:representativeWindow>
            </prj:ScienceSpectralWindow>
            <prj:ScienceSpectralWindow groupResourceUse="FULL">
                <prj:index>0</prj:index>
                <prj:AdvancedWindowSetup smoothingFunction="HANNING">
                    <prj:smoothingFactor>4</prj:smoothingFactor>
                    <prj:oversampling>false</prj:oversampling>
                    <prj:addedSensitivity>false</prj:addedSensitivity>
                    <prj:useImage>false</prj:useImage>
                    <prj:useThis>true</prj:useThis>
                </prj:AdvancedWindowSetup>
                <prj:transitionName>CS</prj:transitionName>
                <prj:centerFrequency unit="GHz">97.311</prj:centerFrequency>
                <prj:bandWidth unit="MHz" userUnit="GHz">2000.0</prj:bandWidth>
                <prj:spectralResolution unit="MHz" userUnit="GHz">0.48828125</prj:spectralResolution>
                <prj:groupIndex>0</prj:groupIndex>
                <prj:isSkyFrequency>false</prj:isSkyFrequency>
                <prj:splatalogId>3952764</prj:splatalogId>
                <prj:representativeWindow>false</prj:representativeWindow>
            </prj:ScienceSpectralWindow>
        </prj:SpectralSetupParameters>
        <prj:TargetParameters solarSystemObject="Unspecified" type="F_MultiplePoints">
            <prj:sourceName>NGC_253</prj:sourceName>
            <prj:sourceCoordinates system="J2000" type="ABSOLUTE">
                <val:longitude unit="deg">11.8879</val:longitude>
                <val:latitude unit="deg">-25.28836111111111</val:latitude>
                <val:fieldName>None</val:fieldName>
            </prj:sourceCoordinates>
            <prj:pmRA unit="mas/yr">0.0</prj:pmRA>
            <prj:pmDec unit="mas/yr">0.0</prj:pmDec>
            <prj:parallax unit="mas">0.0</prj:parallax>
            <prj:nonSiderealMotion>false</prj:nonSiderealMotion>
            <prj:sourceEphemeris></prj:sourceEphemeris>
            <prj:sourceVelocity referenceSystem="lsrk" dopplerCalcType="RELATIVISTIC">
                <val:centerVelocity unit="km/s">230.0</val:centerVelocity>
            </prj:sourceVelocity>
            <prj:index>-1</prj:index>
            <prj:ExpectedProperties>
                <prj:expectedPeakFluxDensity unit="mJy">2.5</prj:expectedPeakFluxDensity>
                <prj:desiredPolarizationPercentage>0.0</prj:desiredPolarizationPercentage>
                <prj:expectedLineWidth unit="GHz" userUnit="km/s">0.009930353691039846</prj:expectedLineWidth>
                <prj:referenceFrequency unit="GHz">99.23483806154033</prj:referenceFrequency>
                <prj:expectedPeakLineFluxDensity unit="mJy">2.0</prj:expectedPeakLineFluxDensity>
                <prj:expectedSpectralDynamicRange>0.0</prj:expectedSpectralDynamicRange>
                <prj:expectedImageDynamicRange>0.0</prj:expectedImageDynamicRange>
                <prj:desiredLinePolarizationPercentage>0.0</prj:desiredLinePolarizationPercentage>
            </prj:ExpectedProperties>
            <prj:isMosaic>false</prj:isMosaic>
            <prj:SinglePoint>
                <prj:name></prj:name>
                <prj:centre system="J2000" type="RELATIVE">
                    <val:longitude unit="arcsec">0.0</val:longitude>
                    <val:latitude unit="arcsec">0.0</val:latitude>
                    <val:fieldName>NGC_253-1</val:fieldName>
                </prj:centre>
            </prj:SinglePoint>
        </prj:TargetParameters>
        <prj:TechnicalJustification>
            <prj:justificationText>To achieve maximum continuum sensitivity, we place four 2 GHz width spectral windows in the correlator setup. The target (NGC 253) is very active starburst galaxy and many molecular and atomic lines have been already detected (e.g. 2 mm line survey by Martin et al. 2006, ApJS 164, 450). To get accurate continuum image, it is indispensable to identify and isolate contamination of those line emission. For this purpose, a spectral (velocity) resolution obtained with the 2 GHz and 128 channel mode is too low (effective resolution is about 90 km/s) and it will cause failing to remove weak and/or narrow velocity width emission lines. Therefore, we request the 2 GHz bandwidth with 3840 channels mode.</prj:justificationText>
            <prj:justificationKey>ED_CORRELATOR</prj:justificationKey>
        </prj:TechnicalJustification>
        <prj:TechnicalJustification>
            <prj:justificationText>Apparent angular sizes of targets in our study are both compact (0.06~0.5 arcseconds) and extended (0.5 ~ a few arcseconds) in both continuum and line. In the science goal, we aim to catch the extended sources, which have been seen in our Cycle 0 data. The maximum angular scale in the other science goal is about 1.1 arcseconds, and it's impossible to recover those extended sources. Hence, we request this science goal with a larger angular scale to recover extended emission.
We request resolution of 0.5 arcsecond which resolves the extended emission and also maximum angular scale is sufficient. The relevant configuration is C36-5, but C36-4 is also acceptable.
The relevant configuration for the other science goal is C36-8 (the min and max baseline lengths are 346 m and 9743 m). The baseline coverage of our Cycle 0 data is from 21 m to 402 m. The overlap is very small; if we try to create an image using a combined data set with them, a synthesized beam shape will not be a good. C36-5 is the best configuration to fill the gap with a sufficient baseline coverage between two data set.</prj:justificationText>
            <prj:justificationKey>ED_ANGULAR_RESOLUTION</prj:justificationKey>
        </prj:TechnicalJustification>
        <prj:TechnicalJustification>
            <prj:justificationText>The primary aim of the observation is to detect H40alpha emission line and continuum in &gt;0.5 arcsec (&gt;10) parsec scale. We expect a target has an average flux density of 2 mJy/beam and a velocity width of 30 km/s. To achieve secure detection in velocity space and also to resolve the emission at the minimum in velocity space, we require 10 km/s velocity resolution. To achieve secure detection we need to achieve a signal-to-noise ratio more than 4, and this requires a map noise level of 0.5 mJy in 10 km/s resolution. About 1.6 hours on-source integration is required to reach the noise level, and a continuum sensitivity with 1.6 hours integration reaches about 10 uJy. The target has typical peak continuum flux density of 2.5 mJy/beam (total flux is ~5 mJy), and the continuum sensitivity is sufficient for detecting it.</prj:justificationText>
            <prj:justificationKey>ED_SENSITIVITY</prj:justificationKey>
        </prj:TechnicalJustification>
    </prj:ScienceGoal>
    <prj:ObsPlan status="NewPhase2" entityPartId="X5039826" almatype="APDM::ObsUnitSet">
        <prj:name>ObsUnitSet</prj:name>
        <prj:note></prj:note>
        <prj:ObsUnitControl arrayRequested="TWELVE-M">
            <prj:maximumTime unit="min">0.0</prj:maximumTime>
            <prj:userPriority>0</prj:userPriority>
            <prj:estimatedExecutionTime unit="min">0.0</prj:estimatedExecutionTime>
            <prj:tacPriority>0</prj:tacPriority>
            <prj:aggregatedExecutionCount>0</prj:aggregatedExecutionCount>
            <prj:CalibrationRequirements>
                <prj:pointingAccuracy unit="arcsec">0.0</prj:pointingAccuracy>
            </prj:CalibrationRequirements>
        </prj:ObsUnitControl>
        <prj:scienceProcessingScript></prj:scienceProcessingScript>
        <prj:runSciencePipeline>false</prj:runSciencePipeline>
    </prj:ObsPlan>
    <prp:ObsProposalEntity entityId="uid://A001/X1ed/X759"
        entityIdEncrypted="-- id encryption not implemented --"
        entityTypeName="ObsProposal" schemaVersion="13"
        documentVersion="1" timestamp="2015-04-23T14:59:49.146"/>
    <prp:DocumentsRef entityId="uid://A001/X1ed/X75a"
        entityTypeName="ObsAttachment" documentVersion="1"/>
    <prp:ObsProjectRef entityId="uid://A001/X1ed/X758"
        entityTypeName="ObsProject" documentVersion="1"/>
    <prp:abstract>We propose a high spatial resolution observation of thermal free-free continuum emission in 105 GHz (Band 3) together with a hydrogen recombination line (H40alpha) toward a nuclear starburst galaxy NGC 253 in the ALMA Cycle 3.
Based on data taken in the ALMA previous cycles, we successfully assessed physical properties of ionized gas. However, the limited spatial resolution data have constrained us to do just rough estimate of those values. Observations with very high spatial resolution down to the compact HII region scale (0.''08=1.3pc) assisted by the long baseline capability will push back the past limitations, and they provide not only ionized gas properties unambiguosly but also essential insights on the nature of the starburst activity.
</prp:abstract>
    <prp:relatedProposals></prp:relatedProposals>
    <prp:previousProposals></prp:previousProposals>
    <prp:dateReceived>2015-04-23T14:59:47.028Z</prp:dateReceived>
    <prp:cycle>2015.1</prp:cycle>
    <prp:scientificCategoryCode>20</prp:scientificCategoryCode>
    <prp:proposalTypeCode>S</prp:proposalTypeCode>
    <prp:scientificCategoryString>Galaxies and Galactic Nuclei</prp:scientificCategoryString>
    <prp:proposalTypeString>Standard</prp:proposalTypeString>
    <prp:keyword>Starbursts, star formation</prp:keyword>
    <prp:keywordCode>20a</prp:keywordCode>
    <prp:PrincipalInvestigator allowedExec="EA" associatedExec="EA">
        <prp:fullName>Kouichiro Nakanishi</prp:fullName>
        <prp:organisation>ALMA Project Office, National Astronomical Observatory of Japan</prp:organisation>
        <prp:eMail>nakanisi.k@nao.ac.jp</prp:eMail>
        <prp:verfiedUser>true</prp:verfiedUser>
        <prp:userId>knakanishi</prp:userId>
        <prp:telephone></prp:telephone>
        <prp:mobile></prp:mobile>
        <prp:index>1</prp:index>
        <prp:organisationId>21497</prp:organisationId>
    </prp:PrincipalInvestigator>
    <prp:CoInvestigator allowedExec="EA" associatedExec="EA">
        <prp:fullName>Kazuo Sorai</prp:fullName>
        <prp:organisation>Faculty of Science, Hokkaido University</prp:organisation>
        <prp:eMail>sorai@astro1.sci.hokudai.ac.jp</prp:eMail>
        <prp:verfiedUser>true</prp:verfiedUser>
        <prp:userId>ksorai</prp:userId>
        <prp:telephone></prp:telephone>
        <prp:mobile></prp:mobile>
        <prp:index>1</prp:index>
        <prp:organisationId>21368</prp:organisationId>
    </prp:CoInvestigator>
    <prp:CoInvestigator allowedExec="EA" associatedExec="EA">
        <prp:fullName>Naomasa Nakai</prp:fullName>
        <prp:organisation>Graduate School of Pure and Applied Sciences, University of Tsukuba</prp:organisation>
        <prp:eMail>nakai@physics.px.tsukuba.ac.jp</prp:eMail>
        <prp:verfiedUser>true</prp:verfiedUser>
        <prp:userId>nakainaomasa</prp:userId>
        <prp:telephone></prp:telephone>
        <prp:mobile></prp:mobile>
        <prp:index>1</prp:index>
        <prp:organisationId>21481</prp:organisationId>
    </prp:CoInvestigator>
    <prp:CoInvestigator allowedExec="EA" associatedExec="EA">
        <prp:fullName>Nario Kuno</prp:fullName>
        <prp:organisation>Graduate School of Pure and Applied Sciences, University of Tsukuba</prp:organisation>
        <prp:eMail>kuno.nario.gt@u.tsukuba.ac.jp</prp:eMail>
        <prp:verfiedUser>true</prp:verfiedUser>
        <prp:userId>kuno</prp:userId>
        <prp:telephone></prp:telephone>
        <prp:mobile></prp:mobile>
        <prp:index>1</prp:index>
        <prp:organisationId>21481</prp:organisationId>
    </prp:CoInvestigator>
    <prp:CoInvestigator allowedExec="EA" associatedExec="EA">
        <prp:fullName>Hajime Sugai</prp:fullName>
        <prp:organisation>Institute for the Physics and Mathematics of the Universe, The University of Tokyo</prp:organisation>
        <prp:eMail>hajime.sugai@ipmu.jp</prp:eMail>
        <prp:verfiedUser>true</prp:verfiedUser>
        <prp:userId>hsugai</prp:userId>
        <prp:telephone></prp:telephone>
        <prp:mobile></prp:mobile>
        <prp:index>1</prp:index>
        <prp:organisationId>21468</prp:organisationId>
    </prp:CoInvestigator>
    <prp:CoInvestigator allowedExec="EA" associatedExec="EA">
        <prp:fullName>Kazuya Matsubayashi</prp:fullName>
        <prp:organisation>Graduate School of Science, Kyoto University</prp:organisation>
        <prp:eMail>kazuya@kusastro.kyoto-u.ac.jp</prp:eMail>
        <prp:verfiedUser>true</prp:verfiedUser>
        <prp:userId>kmatsubayashi</prp:userId>
        <prp:telephone></prp:telephone>
        <prp:mobile></prp:mobile>
        <prp:index>1</prp:index>
        <prp:organisationId>21393</prp:organisationId>
    </prp:CoInvestigator>
    <prp:CoInvestigator allowedExec="EA" associatedExec="EA">
        <prp:fullName>Shuro Takano</prp:fullName>
        <prp:organisation>College of Engineering, Nihon University</prp:organisation>
        <prp:eMail>stakano@ge.ce.nihon-u.ac.jp</prp:eMail>
        <prp:verfiedUser>true</prp:verfiedUser>
        <prp:userId>stakano</prp:userId>
        <prp:telephone></prp:telephone>
        <prp:mobile></prp:mobile>
        <prp:index>1</prp:index>
        <prp:organisationId>36368</prp:organisationId>
    </prp:CoInvestigator>
    <prp:ProposalFeedback>
        <prp:estimatedTotalIntegrationTime unit="s">30265.48</prp:estimatedTotalIntegrationTime>
        <prp:ArrayTimeBreakdown>
            <prp:ArrayTime arrayName="ACA">
                <prp:estimatedTime unit="s">0.0</prp:estimatedTime>
            </prp:ArrayTime>
            <prp:ArrayTime arrayName="SEVEN-M">
                <prp:estimatedTime unit="s">0.0</prp:estimatedTime>
            </prp:ArrayTime>
            <prp:ArrayTime arrayName="TP-Array">
                <prp:estimatedTime unit="s">0.0</prp:estimatedTime>
            </prp:ArrayTime>
            <prp:ArrayTime arrayName="TWELVE-M">
                <prp:estimatedTime unit="s">30265.48</prp:estimatedTime>
            </prp:ArrayTime>
            <prp:ArrayTime arrayName="ALMA">
                <prp:estimatedTime unit="s">30265.48</prp:estimatedTime>
            </prp:ArrayTime>
        </prp:ArrayTimeBreakdown>
        <prp:DataRateBreakdown>
            <prp:ArrayDataRates arrayName="TWELVE-M">
                <prp:estimatedAverageDataRate unit="MB/s">10.681972301826276</prp:estimatedAverageDataRate>
                <prp:estimatedMaximumDataRate unit="MB/s">10.681972301826276</prp:estimatedMaximumDataRate>
                <prp:estimatedDataVolume unit="GB">133.48432842268164</prp:estimatedDataVolume>
            </prp:ArrayDataRates>
            <prp:ArrayDataRates arrayName="SEVEN-M">
                <prp:estimatedAverageDataRate unit="MB/s">0.0</prp:estimatedAverageDataRate>
                <prp:estimatedMaximumDataRate unit="GB/s">0.0</prp:estimatedMaximumDataRate>
                <prp:estimatedDataVolume unit="GB">0.0</prp:estimatedDataVolume>
            </prp:ArrayDataRates>
            <prp:ArrayDataRates arrayName="TP-Array">
                <prp:estimatedAverageDataRate unit="MB/s">0.0</prp:estimatedAverageDataRate>
                <prp:estimatedMaximumDataRate unit="GB/s">0.0</prp:estimatedMaximumDataRate>
                <prp:estimatedDataVolume unit="GB">0.0</prp:estimatedDataVolume>
            </prp:ArrayDataRates>
        </prp:DataRateBreakdown>
        <prp:ReceiverTimeBreakdown>
            <prp:ReceiverTime receiverBand="ALMA_RB_03">
                <prp:time unit="s">30265.48</prp:time>
            </prp:ReceiverTime>
        </prp:ReceiverTimeBreakdown>
        <prp:TimeAllocationBreakdown>
            <prp:ExecutiveFraction name="OTHER">
                <prp:timeFraction>0.0</prp:timeFraction>
            </prp:ExecutiveFraction>
            <prp:ExecutiveFraction name="CL">
                <prp:timeFraction>0.0</prp:timeFraction>
            </prp:ExecutiveFraction>
            <prp:ExecutiveFraction name="EA">
                <prp:timeFraction>1.0</prp:timeFraction>
            </prp:ExecutiveFraction>
            <prp:ExecutiveFraction name="EU">
                <prp:timeFraction>0.0</prp:timeFraction>
            </prp:ExecutiveFraction>
            <prp:ExecutiveFraction name="NA">
                <prp:timeFraction>0.0</prp:timeFraction>
            </prp:ExecutiveFraction>
            <prp:ExecutiveFraction name="NA_EA">
                <prp:timeFraction>0.0</prp:timeFraction>
            </prp:ExecutiveFraction>
        </prp:TimeAllocationBreakdown>
    </prp:ProposalFeedback>
</prp:ObsProposal>
